integrity_check/__init__.py
integrity_check/integrity_check.py
integrity_check-1.3.4.dist-info/LICENSE
integrity_check-1.3.4.dist-info/METADATA
integrity_check-1.3.4.dist-info/WHEEL
integrity_check-1.3.4.dist-info/top_level.txt
integrity_check-1.3.4.dist-info/RECORD
