Metadata-Version: 2.1
Name: integrity-check
Version: 1.3.4
Summary: A replacement for assert
Home-page: https://github.com/ArtFab/integrity-py
Author: ArtFab
Author-email: auz.tin@outlook.com
License: UNKNOWN
Platform: UNKNOWN
Classifier: Programming Language :: Python :: 3
Classifier: License :: OSI Approved :: MIT License
Classifier: Operating System :: OS Independent
Requires-Python: >=3.6
